khronos/__init__.py
khronos/constants.py
khronos/custom_test_runner.py
khronos/service.py
django_khronos-0.1.1.dist-info/LICENSE
django_khronos-0.1.1.dist-info/METADATA
django_khronos-0.1.1.dist-info/WHEEL
django_khronos-0.1.1.dist-info/top_level.txt
django_khronos-0.1.1.dist-info/RECORD
