Metadata-Version: 2.1
Name: django-khronos
Version: 0.1.1
Summary: Khronos is a Python library that benchmarks the duration of Django tests. It helps identify slow-running tests in your test suite, allowing you to optimize their performance.
Home-page: https://github.com/abhinavsp0730/khronos/
Author: Abhinav Prakash
Author-email: abhinavsp0730@gmail.com
License: MIT License
Classifier: Programming Language :: Python :: 3
Classifier: License :: OSI Approved :: MIT License
Classifier: Operating System :: OS Independent
Requires-Python: >=3.9
License-File: LICENSE
Requires-Dist: rich (>=13.3.5)
Requires-Dist: gspread (>=5.9.0)
